sspdatatables/__init__.py
sspdatatables/apps.py
sspdatatables/datatables.py
sspdatatables/forms.py
sspdatatables/templates/datatables/html/table.html
sspdatatables/templates/datatables/js/footer.js
sspdatatables/templates/datatables/js/general.js
sspdatatables/templatetags/__init__.py
sspdatatables/templatetags/form_field.py
sspdatatables/tests/__init__.py
sspdatatables/utils/__init__.py
sspdatatables/utils/data_type_ensure.py
sspdatatables/utils/decorator.py
sspdatatables/utils/enum.py
sspdatatables-0.1.1.dist-info/LICENSE
sspdatatables-0.1.1.dist-info/METADATA
sspdatatables-0.1.1.dist-info/WHEEL
sspdatatables-0.1.1.dist-info/top_level.txt
sspdatatables-0.1.1.dist-info/RECORD
