Metadata-Version: 2.1
Name: sspdatatables
Version: 0.1.1
Summary: Django package serverside processing datatables
Home-page: https://github.com/zhiwei2017/sspdatatables
Author: Zhiwei Zhang
Author-email: zhiwei2017@gmail.com
License: UNKNOWN
Platform: UNKNOWN
Classifier: Programming Language :: Python :: 3
Classifier: License :: OSI Approved :: MIT License
Classifier: Operating System :: OS Independent
Requires-Dist: pytz
Requires-Dist: django
Requires-Dist: djangorestframework
